Ecarx_APITest/__init__.py
Ecarx_APITest/wp.py
Ecarx_APITest-1.0.dist-info/METADATA
Ecarx_APITest-1.0.dist-info/WHEEL
Ecarx_APITest-1.0.dist-info/top_level.txt
Ecarx_APITest-1.0.dist-info/RECORD
