Metadata-Version: 2.1
Name: Ecarx-APITest
Version: 1.0
Summary: 一个非常NB的包
Author: xiaodong.zhu
Author-email: zhuxiaodong45@163.com
License: UNKNOWN
Platform: UNKNOWN
Classifier: Programming Language :: Python :: 3
Classifier: License :: OSI Approved :: MIT License
Classifier: Operating System :: OS Independent
Requires-Python: >=3
Requires-Dist: pillow
